{
  "en": {
    "id": 1935,
    "title": "Soaking Wet",
    "description": "Waterlogged gear is reducing movement speed.",
    "effects": [
      "Waterlogged gear is reducing movement speed."
    ],
    "classification": "debuff",
    "icon": {
      "id": 215995,
      "file": "icon.png",
      "available_in_game_files": true
    },
    "max_stacks": 0,
    "status_category_id": 2,
    "target_type": 0,
    "can_dispel": false,
    "can_remove_manually": false,
    "is_permanent": false,
    "inflicted_by_actor": false,
    "is_fc_buff": false,
    "is_gaze": false,
    "is_invisible": false,
    "party_list_priority": 250,
    "can_increase_rewards": 0,
    "locks": {
      "movement": false,
      "actions": false,
      "control": false
    },
    "transfiguration": false,
    "parameter": {
      "effect": 1,
      "modifier": 0
    },
    "class_job_category": {
      "id": 1,
      "name": "All Classes",
      "allowed_jobs": [
        "ACN",
        "ADV",
        "ALC",
        "ARC",
        "ARM",
        "AST",
        "BLM",
        "BLU",
        "BRD",
        "BSM",
        "BTN",
        "CNJ",
        "CRP",
        "CUL",
        "DNC",
        "DRG",
        "DRK",
        "FSH",
        "GLA",
        "GNB",
        "GSM",
        "LNC",
        "LTW",
        "MCH",
        "MIN",
        "MNK",
        "MRD",
        "NIN",
        "PCT",
        "PGL",
        "PLD",
        "RDM",
        "ROG",
        "RPR",
        "SAM",
        "SCH",
        "SGE",
        "SMN",
        "THM",
        "VPR",
        "WAR",
        "WHM",
        "WVR"
      ]
    },
    "visual": {
      "hit_effect_id": 17,
      "loop_vfx_id": 39,
      "suppress_log_vfx": false
    },
    "log_id": 0,
    "raw_flags": {
      "flags": 0,
      "flag_2": 0
    }
  },
  "de": {
    "id": 1935,
    "title": "Klitschnass",
    "description": "Bewegungsgeschwindigkeit ist verringert, weil die Kleidung durchtränkt ist.",
    "effects": [
      "Bewegungsgeschwindigkeit ist verringert, weil die Kleidung durchtränkt ist."
    ],
    "classification": "debuff",
    "icon": {
      "id": 215995,
      "file": "icon.png",
      "available_in_game_files": true
    },
    "max_stacks": 0,
    "status_category_id": 2,
    "target_type": 0,
    "can_dispel": false,
    "can_remove_manually": false,
    "is_permanent": false,
    "inflicted_by_actor": false,
    "is_fc_buff": false,
    "is_gaze": false,
    "is_invisible": false,
    "party_list_priority": 250,
    "can_increase_rewards": 0,
    "locks": {
      "movement": false,
      "actions": false,
      "control": false
    },
    "transfiguration": false,
    "parameter": {
      "effect": 1,
      "modifier": 0
    },
    "class_job_category": {
      "id": 1,
      "name": "Alle Klassen",
      "allowed_jobs": [
        "ACN",
        "ADV",
        "ALC",
        "ARC",
        "ARM",
        "AST",
        "BLM",
        "BLU",
        "BRD",
        "BSM",
        "BTN",
        "CNJ",
        "CRP",
        "CUL",
        "DNC",
        "DRG",
        "DRK",
        "FSH",
        "GLA",
        "GNB",
        "GSM",
        "LNC",
        "LTW",
        "MCH",
        "MIN",
        "MNK",
        "MRD",
        "NIN",
        "PCT",
        "PGL",
        "PLD",
        "RDM",
        "ROG",
        "RPR",
        "SAM",
        "SCH",
        "SGE",
        "SMN",
        "THM",
        "VPR",
        "WAR",
        "WHM",
        "WVR"
      ]
    },
    "visual": {
      "hit_effect_id": 17,
      "loop_vfx_id": 39,
      "suppress_log_vfx": false
    },
    "log_id": 0,
    "raw_flags": {
      "flags": 0,
      "flag_2": 0
    }
  },
  "fr": {
    "id": 1935,
    "title": "Ruissellement",
    "description": "Trempé jusqu'aux os. La vitesse de déplacement est réduite.",
    "effects": [
      "Trempé jusqu'aux os. La vitesse de déplacement est réduite."
    ],
    "classification": "debuff",
    "icon": {
      "id": 215995,
      "file": "icon.png",
      "available_in_game_files": true
    },
    "max_stacks": 0,
    "status_category_id": 2,
    "target_type": 0,
    "can_dispel": false,
    "can_remove_manually": false,
    "is_permanent": false,
    "inflicted_by_actor": false,
    "is_fc_buff": false,
    "is_gaze": false,
    "is_invisible": false,
    "party_list_priority": 250,
    "can_increase_rewards": 0,
    "locks": {
      "movement": false,
      "actions": false,
      "control": false
    },
    "transfiguration": false,
    "parameter": {
      "effect": 1,
      "modifier": 0
    },
    "class_job_category": {
      "id": 1,
      "name": "Toutes les classes",
      "allowed_jobs": [
        "ACN",
        "ADV",
        "ALC",
        "ARC",
        "ARM",
        "AST",
        "BLM",
        "BLU",
        "BRD",
        "BSM",
        "BTN",
        "CNJ",
        "CRP",
        "CUL",
        "DNC",
        "DRG",
        "DRK",
        "FSH",
        "GLA",
        "GNB",
        "GSM",
        "LNC",
        "LTW",
        "MCH",
        "MIN",
        "MNK",
        "MRD",
        "NIN",
        "PCT",
        "PGL",
        "PLD",
        "RDM",
        "ROG",
        "RPR",
        "SAM",
        "SCH",
        "SGE",
        "SMN",
        "THM",
        "VPR",
        "WAR",
        "WHM",
        "WVR"
      ]
    },
    "visual": {
      "hit_effect_id": 17,
      "loop_vfx_id": 39,
      "suppress_log_vfx": false
    },
    "log_id": 0,
    "raw_flags": {
      "flags": 0,
      "flag_2": 0
    }
  },
  "ja": {
    "id": 1935,
    "title": "ずぶぬれ",
    "description": "ずぶ濡れになり、移動速度が低下した状態。",
    "effects": [
      "ずぶ濡れになり、移動速度が低下した状態。"
    ],
    "classification": "debuff",
    "icon": {
      "id": 215995,
      "file": "icon.png",
      "available_in_game_files": true
    },
    "max_stacks": 0,
    "status_category_id": 2,
    "target_type": 0,
    "can_dispel": false,
    "can_remove_manually": false,
    "is_permanent": false,
    "inflicted_by_actor": false,
    "is_fc_buff": false,
    "is_gaze": false,
    "is_invisible": false,
    "party_list_priority": 250,
    "can_increase_rewards": 0,
    "locks": {
      "movement": false,
      "actions": false,
      "control": false
    },
    "transfiguration": false,
    "parameter": {
      "effect": 1,
      "modifier": 0
    },
    "class_job_category": {
      "id": 1,
      "name": "全クラス",
      "allowed_jobs": [
        "ACN",
        "ADV",
        "ALC",
        "ARC",
        "ARM",
        "AST",
        "BLM",
        "BLU",
        "BRD",
        "BSM",
        "BTN",
        "CNJ",
        "CRP",
        "CUL",
        "DNC",
        "DRG",
        "DRK",
        "FSH",
        "GLA",
        "GNB",
        "GSM",
        "LNC",
        "LTW",
        "MCH",
        "MIN",
        "MNK",
        "MRD",
        "NIN",
        "PCT",
        "PGL",
        "PLD",
        "RDM",
        "ROG",
        "RPR",
        "SAM",
        "SCH",
        "SGE",
        "SMN",
        "THM",
        "VPR",
        "WAR",
        "WHM",
        "WVR"
      ]
    },
    "visual": {
      "hit_effect_id": 17,
      "loop_vfx_id": 39,
      "suppress_log_vfx": false
    },
    "log_id": 0,
    "raw_flags": {
      "flags": 0,
      "flag_2": 0
    }
  }
}
