{
  "en": {
    "id": 5343,
    "title": "Light Vision",
    "description": "Guided by a luminous beacon, increasing movement speed. Invulnerable to Unbecoming.",
    "effects": [
      "Guided by a luminous beacon, increasing movement speed. Invulnerable to Unbecoming."
    ],
    "classification": "buff",
    "icon": {
      "id": 214414,
      "file": "icon.png",
      "available_in_game_files": true
    },
    "max_stacks": 0,
    "status_category_id": 1,
    "target_type": 0,
    "can_dispel": false,
    "can_remove_manually": true,
    "is_permanent": false,
    "inflicted_by_actor": true,
    "is_fc_buff": false,
    "is_gaze": false,
    "is_invisible": false,
    "party_list_priority": 0,
    "can_increase_rewards": 0,
    "locks": {
      "movement": false,
      "actions": false,
      "control": false
    },
    "transfiguration": false,
    "parameter": {
      "effect": 18,
      "modifier": 0
    },
    "class_job_category": {
      "id": 1,
      "name": "All Classes",
      "allowed_jobs": [
        "ACN",
        "ADV",
        "ALC",
        "ARC",
        "ARM",
        "AST",
        "BLM",
        "BLU",
        "BRD",
        "BSM",
        "BTN",
        "CNJ",
        "CRP",
        "CUL",
        "DNC",
        "DRG",
        "DRK",
        "FSH",
        "GLA",
        "GNB",
        "GSM",
        "LNC",
        "LTW",
        "MCH",
        "MIN",
        "MNK",
        "MRD",
        "NIN",
        "PCT",
        "PGL",
        "PLD",
        "RDM",
        "ROG",
        "RPR",
        "SAM",
        "SCH",
        "SGE",
        "SMN",
        "THM",
        "VPR",
        "WAR",
        "WHM",
        "WVR"
      ]
    },
    "visual": {
      "hit_effect_id": 16,
      "loop_vfx_id": 1156,
      "suppress_log_vfx": false
    },
    "log_id": 0,
    "raw_flags": {
      "flags": 6,
      "flag_2": 0
    }
  },
  "de": {
    "id": 5343,
    "title": "Leitendes Licht",
    "description": "Bewegungsgeschwindigkeit ist erhöht und schrittweiser LP-Verlust ist aufgehoben.",
    "effects": [
      "Bewegungsgeschwindigkeit ist erhöht und schrittweiser LP-Verlust ist aufgehoben."
    ],
    "classification": "buff",
    "icon": {
      "id": 214414,
      "file": "icon.png",
      "available_in_game_files": true
    },
    "max_stacks": 0,
    "status_category_id": 1,
    "target_type": 0,
    "can_dispel": false,
    "can_remove_manually": true,
    "is_permanent": false,
    "inflicted_by_actor": true,
    "is_fc_buff": false,
    "is_gaze": false,
    "is_invisible": false,
    "party_list_priority": 0,
    "can_increase_rewards": 0,
    "locks": {
      "movement": false,
      "actions": false,
      "control": false
    },
    "transfiguration": false,
    "parameter": {
      "effect": 18,
      "modifier": 0
    },
    "class_job_category": {
      "id": 1,
      "name": "Alle Klassen",
      "allowed_jobs": [
        "ACN",
        "ADV",
        "ALC",
        "ARC",
        "ARM",
        "AST",
        "BLM",
        "BLU",
        "BRD",
        "BSM",
        "BTN",
        "CNJ",
        "CRP",
        "CUL",
        "DNC",
        "DRG",
        "DRK",
        "FSH",
        "GLA",
        "GNB",
        "GSM",
        "LNC",
        "LTW",
        "MCH",
        "MIN",
        "MNK",
        "MRD",
        "NIN",
        "PCT",
        "PGL",
        "PLD",
        "RDM",
        "ROG",
        "RPR",
        "SAM",
        "SCH",
        "SGE",
        "SMN",
        "THM",
        "VPR",
        "WAR",
        "WHM",
        "WVR"
      ]
    },
    "visual": {
      "hit_effect_id": 16,
      "loop_vfx_id": 1156,
      "suppress_log_vfx": false
    },
    "log_id": 0,
    "raw_flags": {
      "flags": 6,
      "flag_2": 0
    }
  },
  "fr": {
    "id": 5343,
    "title": "Lumière guide",
    "description": "La Lumière qui jaillit de la faille vous guide. La vitesse de déplacement est augmentée et les dégâts périodiques sont annulés.",
    "effects": [
      "La Lumière qui jaillit de la faille vous guide. La vitesse de déplacement est augmentée et les dégâts périodiques sont annulés."
    ],
    "classification": "buff",
    "icon": {
      "id": 214414,
      "file": "icon.png",
      "available_in_game_files": true
    },
    "max_stacks": 0,
    "status_category_id": 1,
    "target_type": 0,
    "can_dispel": false,
    "can_remove_manually": true,
    "is_permanent": false,
    "inflicted_by_actor": true,
    "is_fc_buff": false,
    "is_gaze": false,
    "is_invisible": false,
    "party_list_priority": 0,
    "can_increase_rewards": 0,
    "locks": {
      "movement": false,
      "actions": false,
      "control": false
    },
    "transfiguration": false,
    "parameter": {
      "effect": 18,
      "modifier": 0
    },
    "class_job_category": {
      "id": 1,
      "name": "Toutes les classes",
      "allowed_jobs": [
        "ACN",
        "ADV",
        "ALC",
        "ARC",
        "ARM",
        "AST",
        "BLM",
        "BLU",
        "BRD",
        "BSM",
        "BTN",
        "CNJ",
        "CRP",
        "CUL",
        "DNC",
        "DRG",
        "DRK",
        "FSH",
        "GLA",
        "GNB",
        "GSM",
        "LNC",
        "LTW",
        "MCH",
        "MIN",
        "MNK",
        "MRD",
        "NIN",
        "PCT",
        "PGL",
        "PLD",
        "RDM",
        "ROG",
        "RPR",
        "SAM",
        "SCH",
        "SGE",
        "SMN",
        "THM",
        "VPR",
        "WAR",
        "WHM",
        "WVR"
      ]
    },
    "visual": {
      "hit_effect_id": 16,
      "loop_vfx_id": 1156,
      "suppress_log_vfx": false
    },
    "log_id": 0,
    "raw_flags": {
      "flags": 6,
      "flag_2": 0
    }
  },
  "ja": {
    "id": 5343,
    "title": "光明の導べ",
    "description": "亀裂から差し込んだ光に導かれた状態。移動速度が上昇し、無の侵食によるＨＰ減少効果を無効化する。",
    "effects": [
      "亀裂から差し込んだ光に導かれた状態。移動速度が上昇し、無の侵食によるＨＰ減少効果を無効化する。"
    ],
    "classification": "buff",
    "icon": {
      "id": 214414,
      "file": "icon.png",
      "available_in_game_files": true
    },
    "max_stacks": 0,
    "status_category_id": 1,
    "target_type": 0,
    "can_dispel": false,
    "can_remove_manually": true,
    "is_permanent": false,
    "inflicted_by_actor": true,
    "is_fc_buff": false,
    "is_gaze": false,
    "is_invisible": false,
    "party_list_priority": 0,
    "can_increase_rewards": 0,
    "locks": {
      "movement": false,
      "actions": false,
      "control": false
    },
    "transfiguration": false,
    "parameter": {
      "effect": 18,
      "modifier": 0
    },
    "class_job_category": {
      "id": 1,
      "name": "全クラス",
      "allowed_jobs": [
        "ACN",
        "ADV",
        "ALC",
        "ARC",
        "ARM",
        "AST",
        "BLM",
        "BLU",
        "BRD",
        "BSM",
        "BTN",
        "CNJ",
        "CRP",
        "CUL",
        "DNC",
        "DRG",
        "DRK",
        "FSH",
        "GLA",
        "GNB",
        "GSM",
        "LNC",
        "LTW",
        "MCH",
        "MIN",
        "MNK",
        "MRD",
        "NIN",
        "PCT",
        "PGL",
        "PLD",
        "RDM",
        "ROG",
        "RPR",
        "SAM",
        "SCH",
        "SGE",
        "SMN",
        "THM",
        "VPR",
        "WAR",
        "WHM",
        "WVR"
      ]
    },
    "visual": {
      "hit_effect_id": 16,
      "loop_vfx_id": 1156,
      "suppress_log_vfx": false
    },
    "log_id": 0,
    "raw_flags": {
      "flags": 6,
      "flag_2": 0
    }
  }
}
