{
  "en": {
    "id": 1933,
    "title": "Army's Ethos",
    "description": "Singing Mage's Ballad or the Wanderer's Minuet will grant the effect of Army's Muse.",
    "effects": [
      "Singing Mage's Ballad or the Wanderer's Minuet will grant the effect of Army's Muse."
    ],
    "classification": "buff",
    "icon": {
      "id": 212620,
      "file": "icon.png",
      "available_in_game_files": true
    },
    "max_stacks": 0,
    "status_category_id": 1,
    "target_type": 0,
    "can_dispel": false,
    "can_remove_manually": false,
    "is_permanent": false,
    "inflicted_by_actor": false,
    "is_fc_buff": false,
    "is_gaze": false,
    "is_invisible": false,
    "party_list_priority": 1,
    "can_increase_rewards": 0,
    "locks": {
      "movement": false,
      "actions": false,
      "control": false
    },
    "transfiguration": false,
    "parameter": {
      "effect": 0,
      "modifier": 0
    },
    "class_job_category": {
      "id": 24,
      "name": "BRD",
      "allowed_jobs": [
        "BRD"
      ]
    },
    "visual": {
      "hit_effect_id": 16,
      "loop_vfx_id": 0,
      "suppress_log_vfx": false
    },
    "log_id": 0,
    "raw_flags": {
      "flags": 0,
      "flag_2": 0
    }
  },
  "de": {
    "id": 1933,
    "title": "Beistand des Schlachtensängers",
    "description": "Gewährt Gunst des Schlachtensängers beim Ausführen von Ballade des Weisen, Menuett des Wanderers oder Hymne der Krieger.",
    "effects": [
      "Gewährt Gunst des Schlachtensängers beim Ausführen von Ballade des Weisen, Menuett des Wanderers oder Hymne der Krieger."
    ],
    "classification": "buff",
    "icon": {
      "id": 212620,
      "file": "icon.png",
      "available_in_game_files": true
    },
    "max_stacks": 0,
    "status_category_id": 1,
    "target_type": 0,
    "can_dispel": false,
    "can_remove_manually": false,
    "is_permanent": false,
    "inflicted_by_actor": false,
    "is_fc_buff": false,
    "is_gaze": false,
    "is_invisible": false,
    "party_list_priority": 1,
    "can_increase_rewards": 0,
    "locks": {
      "movement": false,
      "actions": false,
      "control": false
    },
    "transfiguration": false,
    "parameter": {
      "effect": 0,
      "modifier": 0
    },
    "class_job_category": {
      "id": 24,
      "name": "BRD",
      "allowed_jobs": [
        "BRD"
      ]
    },
    "visual": {
      "hit_effect_id": 16,
      "loop_vfx_id": 0,
      "suppress_log_vfx": false
    },
    "log_id": 0,
    "raw_flags": {
      "flags": 0,
      "flag_2": 0
    }
  },
  "fr": {
    "id": 1933,
    "title": "Pacte martial",
    "description": "Bénédiction martiale est octroyée lorsque Ballade du mage, Péan martial ou Menuet du Vagabond est utilisé.",
    "effects": [
      "Bénédiction martiale est octroyée lorsque Ballade du mage, Péan martial ou Menuet du Vagabond est utilisé."
    ],
    "classification": "buff",
    "icon": {
      "id": 212620,
      "file": "icon.png",
      "available_in_game_files": true
    },
    "max_stacks": 0,
    "status_category_id": 1,
    "target_type": 0,
    "can_dispel": false,
    "can_remove_manually": false,
    "is_permanent": false,
    "inflicted_by_actor": false,
    "is_fc_buff": false,
    "is_gaze": false,
    "is_invisible": false,
    "party_list_priority": 1,
    "can_increase_rewards": 0,
    "locks": {
      "movement": false,
      "actions": false,
      "control": false
    },
    "transfiguration": false,
    "parameter": {
      "effect": 0,
      "modifier": 0
    },
    "class_job_category": {
      "id": 24,
      "name": "BRD",
      "allowed_jobs": [
        "BRD"
      ]
    },
    "visual": {
      "hit_effect_id": 16,
      "loop_vfx_id": 0,
      "suppress_log_vfx": false
    },
    "log_id": 0,
    "raw_flags": {
      "flags": 0,
      "flag_2": 0
    }
  },
  "ja": {
    "id": 1933,
    "title": "軍神の契約",
    "description": "賢人のバラード、軍神のパイオン、旅神のメヌエットを実行すると「軍神の加護」が付与される状態。",
    "effects": [
      "賢人のバラード、軍神のパイオン、旅神のメヌエットを実行すると「軍神の加護」が付与される状態。"
    ],
    "classification": "buff",
    "icon": {
      "id": 212620,
      "file": "icon.png",
      "available_in_game_files": true
    },
    "max_stacks": 0,
    "status_category_id": 1,
    "target_type": 0,
    "can_dispel": false,
    "can_remove_manually": false,
    "is_permanent": false,
    "inflicted_by_actor": false,
    "is_fc_buff": false,
    "is_gaze": false,
    "is_invisible": false,
    "party_list_priority": 1,
    "can_increase_rewards": 0,
    "locks": {
      "movement": false,
      "actions": false,
      "control": false
    },
    "transfiguration": false,
    "parameter": {
      "effect": 0,
      "modifier": 0
    },
    "class_job_category": {
      "id": 24,
      "name": "吟遊詩人",
      "allowed_jobs": [
        "BRD"
      ]
    },
    "visual": {
      "hit_effect_id": 16,
      "loop_vfx_id": 0,
      "suppress_log_vfx": false
    },
    "log_id": 0,
    "raw_flags": {
      "flags": 0,
      "flag_2": 0
    }
  }
}
